{"batchcomplete": "", "query": {"pages": {"51978750": {"pageid": 51978750, "ns": 0, "title": "Donald Trump sexual misconduct allegations", "contentmodel": "wikitext", "pagelanguage": "en", "pagelanguagehtmlcode": "en", "pagelanguagedir": "ltr", "touched": "2026-02-27T06:38:18Z", "lastrevid": 1340653294, "length": 218915, "fullurl": "https://en.wikipedia.org/wiki/Donald_Trump_sexual_misconduct_allegations", "editurl": "https://en.wikipedia.org/w/index.php?title=Donald_Trump_sexual_misconduct_allegations&action=edit", "canonicalurl": "https://en.wikipedia.org/wiki/Donald_Trump_sexual_misconduct_allegations", "pageprops": {"defaultsort": "Trump, Donald", "wikibase-shortdesc": "", "wikibase_item": "Q27243341"}, "description": "", "descriptionsource": "local", "extract": "Since the 1970s, at least 28 women have accused Donald Trump of various acts of sexual misconduct, including rape, assault,  kissing and groping without consent, looking under women's skirts, and walking in on naked pageant contestants. He has a history of insulting and belittling women when speaking to the media and on social media, and has made lewd comments about women, disparaged their physical appearance, and referred to them using derogatory epithets. \nTrump told Howard Stern on his radio show in 2005 that \"he got away with going backstage when the contestants were naked\" at beauty pageants. In October 2016, two days before the second presidential debate with Hillary Clinton, a 2005 \"hot mic\" recording surfaced in which Trump was heard saying that \"when you're a star, they let you do it. You can do anything. ... Grab 'em by the pussy.\" The incident's widespread media exposure led to Trump's first public apology during the campaign, and caused outrage across the political spectrum.\nIn 2025, Trump's past friendship with Jeffrey Epstein received significant media attention following his administration's refusal to release files relating to Epstein, despite Trump's 2024 election campaign promises to do so. In response to the passage of the Epstein Files Transparency Act, the files were eventually released. They revealed other accounts of Trump's alleged sexual misconduct that were investigated by the FBI.", "categories": [{"ns": 14, "title": "Category:All Wikipedia articles written in American English"}, {"ns": 14, "title": "Category:All articles containing potentially dated statements"}, {"ns": 14, "title": "Category:All articles with specifically marked weasel-worded phrases"}, {"ns": 14, "title": "Category:All articles with unsourced statements"}, {"ns": 14, "title": "Category:All articles with vague or ambiguous time"}, {"ns": 14, "title": "Category:Articles containing potentially dated statements from February 2026"}, {"ns": 14, "title": "Category:Articles containing potentially dated statements from September 2018"}, {"ns": 14, "title": "Category:Articles containing video clips"}, {"ns": 14, "title": "Category:Articles with excerpts"}, {"ns": 14, "title": "Category:Articles with short description"}, {"ns": 14, "title": "Category:Articles with specifically marked weasel-worded phrases from May 2024"}, {"ns": 14, "title": "Category:Articles with unsourced statements from December 2025"}, {"ns": 14, "title": "Category:CS1 Finnish-language sources (fi)"}, {"ns": 14, "title": "Category:CS1 maint: multiple names: authors list"}, {"ns": 14, "title": "Category:Child sexual abuse cover-ups"}, {"ns": 14, "title": "Category:Controversies of the 2016 United States presidential election"}, {"ns": 14, "title": "Category:Donald Trump controversies"}, {"ns": 14, "title": "Category:Federal political sex scandals in the United States"}, {"ns": 14, "title": "Category:Jeffrey Epstein"}, {"ns": 14, "title": "Category:October 2016 in the United States"}, {"ns": 14, "title": "Category:Sexual misconduct allegations"}, {"ns": 14, "title": "Category:Short description is different from Wikidata"}, {"ns": 14, "title": "Category:Trump administration controversies"}, {"ns": 14, "title": "Category:Use American English from February 2026"}, {"ns": 14, "title": "Category:Use mdy dates from August 2023"}, {"ns": 14, "title": "Category:Vague or ambiguous time from May 2023"}, {"ns": 14, "title": "Category:Wikipedia pages semi-protected against vandalism"}]}}}, "limits": {"categories": 500}}