{"query": {"search": [{"ns": 0, "title": "L. S. Lowry", "pageid": 208019, "size": 67339, "wordcount": 6883, "snippet": "Fever Van&#039;, <span class=\"searchmatch\">L.S</span>. <span class=\"searchmatch\">Lowry</span>&quot;. Liverpool museums. Retrieved 1 November 2012. &quot;<span class=\"searchmatch\">L.S</span>. <span class=\"searchmatch\">Lowry</span> Laying a Foundation Stone 1936 <span class=\"searchmatch\">L.S</span>. <span class=\"searchmatch\">Lowry</span>&quot;. <span class=\"searchmatch\">Ls</span>-<span class=\"searchmatch\">lowry</span>.com. Archived", "timestamp": "2026-02-17T07:23:22Z"}, {"ns": 0, "title": "The Lowry", "pageid": 3641642, "size": 18836, "wordcount": 1769, "snippet": "related to The <span class=\"searchmatch\">Lowry</span>. Official website Online exhibition of the <span class=\"searchmatch\">Lowry</span> art collection &quot;Work by <span class=\"searchmatch\">LS</span> <span class=\"searchmatch\">Lowry</span>: People&quot;. thelowry.com. Salford: The <span class=\"searchmatch\">Lowry</span>. Archived", "timestamp": "2026-01-25T22:56:54Z"}, {"ns": 0, "title": "Going to the Match", "pageid": 73563527, "size": 16139, "wordcount": 1465, "snippet": " 222. &quot;The earliest known sports painting by <span class=\"searchmatch\">LS</span> <span class=\"searchmatch\">Lowry</span> set to go on view | Latest News&quot;. thelowry.com. The <span class=\"searchmatch\">Lowry</span>. 1 June 2021. Archived from the original on", "timestamp": "2025-11-28T23:55:09Z"}, {"ns": 0, "title": "Andrew Law (financier)", "pageid": 45322473, "size": 13237, "wordcount": 1211, "snippet": "2022, the foundation provided the £8.1 million funding for the <span class=\"searchmatch\">Lowry</span> to purchase <span class=\"searchmatch\">L.S</span>.<span class=\"searchmatch\">Lowry&#039;s</span> Going to the Match, the 1953 painting of people on their way", "timestamp": "2026-02-11T18:20:44Z"}, {"ns": 0, "title": "Going to Work", "pageid": 72744125, "size": 10167, "wordcount": 970, "snippet": "industrial haze. The painting is signed in the bottom-left corner &quot;<span class=\"searchmatch\">L.S</span>.<span class=\"searchmatch\">LOWRY</span> 1943&quot;. <span class=\"searchmatch\">Lowry</span> painted the scene during a period of reduced artistic activity in", "timestamp": "2026-01-12T02:59:16Z"}, {"ns": 0, "title": "Peel Park, Salford", "pageid": 19165846, "size": 23753, "wordcount": 2858, "snippet": "has been the subject of a number of paintings by the Salford artist, <span class=\"searchmatch\">L.S</span>. <span class=\"searchmatch\">Lowry</span>. Peel Park fell into disrepair during the latter part of the 20th century", "timestamp": "2026-01-18T21:47:55Z"}, {"ns": 0, "title": "Coming from the Mill", "pageid": 50426594, "size": 10500, "wordcount": 1029, "snippet": "Retrieved 4 May 2016. <span class=\"searchmatch\">LS</span> <span class=\"searchmatch\">Lowry&#039;s</span> Coming from the Mill. YouTube.com. The <span class=\"searchmatch\">Lowry</span>. 29 July 2019. Retrieved 1 January 2023. &quot;<span class=\"searchmatch\">LS</span> <span class=\"searchmatch\">Lowry</span> – His Life and Career&quot;", "timestamp": "2025-02-15T04:04:53Z"}, {"ns": 0, "title": "Industrial Landscape", "pageid": 73283860, "size": 11383, "wordcount": 1239, "snippet": "around the United Kingdom, such as The <span class=\"searchmatch\">Lowry</span> in Salford, while others are in private collections. <span class=\"searchmatch\">L.S</span>. <span class=\"searchmatch\">Lowry</span> was born in 1887 in Stretford, Lancashire", "timestamp": "2025-12-30T06:55:42Z"}, {"ns": 0, "title": "Pendlebury railway station", "pageid": 5823993, "size": 9231, "wordcount": 913, "snippet": "www.railwaysarchive.co.uk. Retrieved 14 March 2023. &quot;<span class=\"searchmatch\">LS</span> <span class=\"searchmatch\">Lowry</span> – His Life and Career&quot;. The <span class=\"searchmatch\">Lowry</span>. Archived from the original on 2 May 2012. Retrieved 28", "timestamp": "2025-12-20T14:11:00Z"}, {"ns": 0, "title": "The Lowry Academy", "pageid": 44091336, "size": 11480, "wordcount": 740, "snippet": "Educating... TV series. The school is named after the noted Salford artist, <span class=\"searchmatch\">L.S</span>. <span class=\"searchmatch\">Lowry</span>. The school was formed in 2001 from the merger of Joseph Eastham High", "timestamp": "2026-01-25T14:16:09Z"}]}, "continue": {"sroffset": 10, "continue": "-||"}}