{"batchcomplete": "", "query": {"pages": {"11153712": {"pageid": 11153712, "ns": 0, "title": "King George V Silver Jubilee Medal", "contentmodel": "wikitext", "pagelanguage": "en", "pagelanguagehtmlcode": "en", "pagelanguagedir": "ltr", "touched": "2026-02-20T22:09:41Z", "lastrevid": 1333891785, "length": 18573, "fullurl": "https://en.wikipedia.org/wiki/King_George_V_Silver_Jubilee_Medal", "editurl": "https://en.wikipedia.org/w/index.php?title=King_George_V_Silver_Jubilee_Medal&action=edit", "canonicalurl": "https://en.wikipedia.org/wiki/King_George_V_Silver_Jubilee_Medal", "pageprops": {"toc": "", "wikibase-shortdesc": "Award", "wikibase_item": "Q1885471"}, "description": "Award", "descriptionsource": "local", "extract": "The King George V Silver Jubilee Medal is a commemorative medal, instituted to celebrate the 25th anniversary of the accession of King George V.", "categories": [{"ns": 14, "title": "Category:1935 establishments in the United Kingdom"}, {"ns": 14, "title": "Category:All Wikipedia articles written in British English"}, {"ns": 14, "title": "Category:Articles with short description"}, {"ns": 14, "title": "Category:Awards disestablished in 1935"}, {"ns": 14, "title": "Category:Awards established in 1935"}, {"ns": 14, "title": "Category:Civil awards and decorations of Australia"}, {"ns": 14, "title": "Category:Civil awards and decorations of Canada"}, {"ns": 14, "title": "Category:Civil awards and decorations of New Zealand"}, {"ns": 14, "title": "Category:Civil awards and decorations of the United Kingdom"}, {"ns": 14, "title": "Category:George V"}, {"ns": 14, "title": "Category:Military decorations and medals of South Africa pre-1952"}, {"ns": 14, "title": "Category:Short description with empty Wikidata description"}, {"ns": 14, "title": "Category:Silver Jubilee of George V"}, {"ns": 14, "title": "Category:Use British English from May 2011"}, {"ns": 14, "title": "Category:Use dmy dates from December 2021"}]}}}, "limits": {"categories": 500}}