{"batchcomplete": "", "query": {"pages": {"1536396": {"pageid": 1536396, "ns": 0, "title": "I'm Talking", "contentmodel": "wikitext", "pagelanguage": "en", "pagelanguagehtmlcode": "en", "pagelanguagedir": "ltr", "touched": "2026-02-19T15:12:31Z", "lastrevid": 1338885388, "length": 25227, "fullurl": "https://en.wikipedia.org/wiki/I%27m_Talking", "editurl": "https://en.wikipedia.org/w/index.php?title=I%27m_Talking&action=edit", "canonicalurl": "https://en.wikipedia.org/wiki/I%27m_Talking", "pageprops": {"wikibase-shortdesc": "Australian pop band", "wikibase_item": "Q12656535"}, "description": "Australian pop band", "descriptionsource": "local", "extract": "I'm Talking were an Australian funk-pop rock band, which featured vocalists Kate Ceberano and Zan Abeyratne. They formed in 1983 in Melbourne and provided top ten hit singles \"Trust Me\", \"Do You Wanna Be?\" and \"Holy Word\" and a top fifteen album, Bear Witness, before disbanding in 1987. The group reunited in October 2018, and went on a 2019 tour as well as a series of small venue shows.\n\n", "categories": [{"ns": 14, "title": "Category:1983 establishments in Australia"}, {"ns": 14, "title": "Category:2020 disestablishments in Australia"}, {"ns": 14, "title": "Category:All Wikipedia articles written in Australian English"}, {"ns": 14, "title": "Category:All articles with dead external links"}, {"ns": 14, "title": "Category:Articles with dead external links from February 2026"}, {"ns": 14, "title": "Category:Articles with hCards"}, {"ns": 14, "title": "Category:Articles with short description"}, {"ns": 14, "title": "Category:Australian electronic dance music groups"}, {"ns": 14, "title": "Category:CS1: unfit URL"}, {"ns": 14, "title": "Category:Kate Ceberano"}, {"ns": 14, "title": "Category:Musical groups disestablished in 2020"}, {"ns": 14, "title": "Category:Musical groups established in 1983"}, {"ns": 14, "title": "Category:Musical groups from Melbourne"}, {"ns": 14, "title": "Category:Pages using infobox musical artist with associated acts"}, {"ns": 14, "title": "Category:Short description matches Wikidata"}, {"ns": 14, "title": "Category:Use Australian English from September 2016"}, {"ns": 14, "title": "Category:Use dmy dates from September 2016"}]}}}, "limits": {"categories": 500}}