{"batchcomplete": "", "query": {"pages": {"2336422": {"pageid": 2336422, "ns": 0, "title": "Orla Brady", "contentmodel": "wikitext", "pagelanguage": "en", "pagelanguagehtmlcode": "en", "pagelanguagedir": "ltr", "touched": "2026-02-26T17:39:02Z", "lastrevid": 1334875589, "length": 29876, "fullurl": "https://en.wikipedia.org/wiki/Orla_Brady", "editurl": "https://en.wikipedia.org/w/index.php?title=Orla_Brady&action=edit", "canonicalurl": "https://en.wikipedia.org/wiki/Orla_Brady", "pageprops": {"defaultsort": "Brady, Orla", "page_image_free": "Orla_Brady_2020_1_cropped.jpg", "wikibase-shortdesc": "Irish actress (born 1961)", "wikibase_item": "Q444292"}, "description": "Irish actress (born 1961)", "descriptionsource": "local", "extract": "Orla Brady (born 28 March 1961) is an Irish theatre, television, and film actress born in Dublin. Named in 2020 by The Irish Times as one of Ireland's greatest actors, she has received seven IFTA Award (Irish Film & Television Academy) nominations, a Saturn Award nomination, the Abbey Theatre Award, and Best Actress from the Monte Carlo International Film Festival.   \nBrady's diverse television credits include Into the Badlands (2016-2019), Mistresses (2008-2010), Star Trek: Picard (2022), Bosch: Legacy (2025), Fringe (2008-2013), Banished (2015), Doctor Who (2013), American Odyssey (2015), American Horror Story (2018), and VisionQuest (2026). On film, Brady's credits include her Award-winning performance in A Love Divided (1999), The Luzhin Defence (2000), Silent Grace (2001), The Foreigner (2017), Rose Plays Julie (2019), and opposite Anthony Hopkins in Freud's Last Session (2023).   \nBrady trained at École Philippe Gaulier in Paris before an extensive stage career in Dublin and London, starring at the Royal National Theatre, the Abbey Theatre, the Gate Theatre, and on the West End. In 2019, She won the Abbey Theatre Award for her performance in On Broken Wings.", "categories": [{"ns": 14, "title": "Category:1961 births"}, {"ns": 14, "title": "Category:20th-century Irish actresses"}, {"ns": 14, "title": "Category:21st-century Irish actresses"}, {"ns": 14, "title": "Category:Actresses from County Wicklow"}, {"ns": 14, "title": "Category:Actresses from Dublin (city)"}, {"ns": 14, "title": "Category:All Wikipedia articles written in Hiberno-English"}, {"ns": 14, "title": "Category:Articles containing French-language text"}, {"ns": 14, "title": "Category:Articles with hCards"}, {"ns": 14, "title": "Category:Articles with short description"}, {"ns": 14, "title": "Category:Commons category link from Wikidata"}, {"ns": 14, "title": "Category:Former Roman Catholics"}, {"ns": 14, "title": "Category:Irish atheists"}, {"ns": 14, "title": "Category:Irish expatriate actresses in the United States"}, {"ns": 14, "title": "Category:Irish film actresses"}, {"ns": 14, "title": "Category:Irish stage actresses"}, {"ns": 14, "title": "Category:Irish television actresses"}, {"ns": 14, "title": "Category:Living people"}, {"ns": 14, "title": "Category:People from Bray, County Wicklow"}, {"ns": 14, "title": "Category:Short description is different from Wikidata"}, {"ns": 14, "title": "Category:Use Hiberno-English from May 2014"}, {"ns": 14, "title": "Category:Use dmy dates from December 2021"}]}}}, "limits": {"categories": 500}}