{"query": {"search": [{"ns": 0, "title": "Rhun ap Iorwerth", "pageid": 40134345, "size": 20000, "wordcount": 1679, "snippet": "<span class=\"searchmatch\">Rhun</span> <span class=\"searchmatch\">ap</span> <span class=\"searchmatch\">Iorwerth</span> (Welsh pronunciation: [r̥ɨːn <span class=\"searchmatch\">ap</span> ˈjɔrwɛrθ]; born 27 August 1972) is a Welsh politician and journalist who has served as the Leader of Plaid", "timestamp": "2026-01-27T20:21:29Z"}, {"ns": 0, "title": "2024 United Kingdom general election", "pageid": 62193830, "size": 342146, "wordcount": 22306, "snippet": "of England and Wales from Siân Berry and Jonathan Bartley in 2021. <span class=\"searchmatch\">Rhun</span> <span class=\"searchmatch\">ap</span> <span class=\"searchmatch\">Iorwerth</span> took over leadership of Plaid Cymru. The Brexit Party rebranded as", "timestamp": "2026-02-24T05:02:10Z"}, {"ns": 0, "title": "Plaid Cymru", "pageid": 53343, "size": 147691, "wordcount": 11752, "snippet": "the party to prevent sexual harassment and bullying. In June 2023 <span class=\"searchmatch\">Rhun</span> <span class=\"searchmatch\">ap</span> <span class=\"searchmatch\">Iorwerth</span> was elected unopposed as leader. The party won both its target seats", "timestamp": "2026-02-27T03:06:22Z"}, {"ns": 0, "title": "Frontbench Team of Rhun ap Iorwerth", "pageid": 77106945, "size": 18661, "wordcount": 907, "snippet": "<span class=\"searchmatch\">Rhun</span> <span class=\"searchmatch\">ap</span> <span class=\"searchmatch\">Iorwerth</span>, the leader of Plaid Cymru, formed his frontbench team of party spokespeople in the Senedd on 27 June 2023 after he was elected unopposed", "timestamp": "2026-02-19T00:11:55Z"}, {"ns": 0, "title": "Iorwerth", "pageid": 21884126, "size": 1907, "wordcount": 256, "snippet": "Wales <span class=\"searchmatch\">Rhun</span> <span class=\"searchmatch\">ap</span> <span class=\"searchmatch\">Iorwerth</span>, leader of Plaid Cymru and Member of the Senedd for Ynys Môn Iolo Iori (disambiguation) Yorath Campbell, Mike. &quot;<span class=\"searchmatch\">Iorwerth</span>&quot;. Behind", "timestamp": "2026-02-08T19:22:36Z"}, {"ns": 0, "title": "2026 Senedd election", "pageid": 68245236, "size": 61232, "wordcount": 2388, "snippet": "the temperature and raise trust.&quot; A day later, Plaid Cymru leader <span class=\"searchmatch\">Rhun</span> <span class=\"searchmatch\">ap</span> <span class=\"searchmatch\">Iorwerth</span> similarly ruled out working with Reform, describing the two parties&#039;", "timestamp": "2026-02-26T18:26:07Z"}, {"ns": 0, "title": "Mabon ap Gwynfor", "pageid": 67604860, "size": 9703, "wordcount": 651, "snippet": "Meirionnydd&quot;. BBC News. Retrieved 7 May 2021. &quot;Plaid Cymru Leader <span class=\"searchmatch\">Rhun</span> <span class=\"searchmatch\">ap</span> <span class=\"searchmatch\">Iorwerth</span> announces make up of Senedd team &quot;dedicated to a fairer, greener, ambitious", "timestamp": "2026-02-22T09:54:11Z"}, {"ns": 0, "title": "Next United Kingdom general election", "pageid": 77189683, "size": 24581, "wordcount": 2377, "snippet": "McDonald 7 Green (E&amp;W) Zack Polanski 5 DUP Gavin Robinson 5 Plaid Cymru <span class=\"searchmatch\">Rhun</span> <span class=\"searchmatch\">ap</span> <span class=\"searchmatch\">Iorwerth</span> 4 SDLP Claire Hanna 2 Alliance Naomi Long 1 UUP Jon Burrows 1 TUV Jim", "timestamp": "2026-02-27T09:06:47Z"}, {"ns": 0, "title": "Rhun Hir ap Maelgwn", "pageid": 1157898, "size": 16947, "wordcount": 1943, "snippet": "<span class=\"searchmatch\">Rhun</span> <span class=\"searchmatch\">ap</span> Maelgwn Gwynedd (died c. 586), also known as <span class=\"searchmatch\">Rhun</span> Hir <span class=\"searchmatch\">ap</span> Maelgwn Gwynedd (English: <span class=\"searchmatch\">Rhun</span> the Tall, son of Maelgwn Gwynedd), sometimes spelt as", "timestamp": "2025-06-30T22:02:43Z"}, {"ns": 0, "title": "Vaughan Gething", "pageid": 31756803, "size": 50011, "wordcount": 3946, "snippet": "choice being made.&quot; Gething denied allegations of perjury put to him by <span class=\"searchmatch\">Rhun</span> <span class=\"searchmatch\">ap</span> <span class=\"searchmatch\">Iorwerth</span> in First Minister&#039;s Questions the same day, describing the allegations", "timestamp": "2025-11-05T14:09:05Z"}]}, "continue": {"sroffset": 10, "continue": "-||"}}