{"batchcomplete": "", "query": {"pages": {"1176688": {"pageid": 1176688, "ns": 0, "title": "Ollie Johnston", "contentmodel": "wikitext", "pagelanguage": "en", "pagelanguagehtmlcode": "en", "pagelanguagedir": "ltr", "touched": "2026-02-26T17:32:54Z", "lastrevid": 1338654638, "length": 19626, "fullurl": "https://en.wikipedia.org/wiki/Ollie_Johnston", "editurl": "https://en.wikipedia.org/w/index.php?title=Ollie_Johnston&action=edit", "canonicalurl": "https://en.wikipedia.org/wiki/Ollie_Johnston", "pageprops": {"defaultsort": "Johnston, Ollie", "page_image_free": "OLLIE1989.jpg", "wikibase-shortdesc": "American animator (1912–2008)", "wikibase_item": "Q443540"}, "description": "American animator (1912–2008)", "descriptionsource": "local", "extract": "Oliver Martin Johnston Jr. (October 31, 1912 – April 14, 2008) was an American motion picture animator. He was one of Disney's Nine Old Men, and the last surviving at the time of his death from natural causes. He was recognized by The Walt Disney Company with its Disney Legend Award in 1989. His work was recognized with the National Medal of Arts in 2005.", "categories": [{"ns": 14, "title": "Category:1912 births"}, {"ns": 14, "title": "Category:2008 deaths"}, {"ns": 14, "title": "Category:20th-century American artists"}, {"ns": 14, "title": "Category:20th-century American writers"}, {"ns": 14, "title": "Category:American animated film directors"}, {"ns": 14, "title": "Category:Animators from California"}, {"ns": 14, "title": "Category:Articles with hCards"}, {"ns": 14, "title": "Category:Articles with short description"}, {"ns": 14, "title": "Category:CS1 maint: location missing publisher"}, {"ns": 14, "title": "Category:Chouinard Art Institute alumni"}, {"ns": 14, "title": "Category:Commons category link is on Wikidata"}, {"ns": 14, "title": "Category:Film directors from California"}, {"ns": 14, "title": "Category:Palo Alto High School alumni"}, {"ns": 14, "title": "Category:People from Julian, California"}, {"ns": 14, "title": "Category:Short description is different from Wikidata"}, {"ns": 14, "title": "Category:Stanford University alumni"}, {"ns": 14, "title": "Category:United States National Medal of Arts recipients"}, {"ns": 14, "title": "Category:University of California, Berkeley alumni"}, {"ns": 14, "title": "Category:Walt Disney Animation Studios people"}, {"ns": 14, "title": "Category:Writers from Palo Alto, California"}]}}}, "limits": {"categories": 500}}