{"batchcomplete": "", "query": {"pages": {"79919785": {"pageid": 79919785, "ns": 0, "title": "2025–26 Swindon Town F.C. season", "contentmodel": "wikitext", "pagelanguage": "en", "pagelanguagehtmlcode": "en", "pagelanguagedir": "ltr", "touched": "2026-02-21T17:50:54Z", "lastrevid": 1339439546, "length": 99135, "fullurl": "https://en.wikipedia.org/wiki/2025%E2%80%9326_Swindon_Town_F.C._season", "editurl": "https://en.wikipedia.org/w/index.php?title=2025%E2%80%9326_Swindon_Town_F.C._season&action=edit", "canonicalurl": "https://en.wikipedia.org/wiki/2025%E2%80%9326_Swindon_Town_F.C._season", "pageprops": {"defaultsort": "2025-26 Swindon Town F.C. season", "wikibase-shortdesc": "147th season in existence of Swindon Town FC", "wikibase_item": "Q134563502"}, "description": "147th season in existence of Swindon Town FC", "descriptionsource": "local", "extract": "The 2025–26 season is the 147th season in the history of Swindon Town Football Club and their fifth consecutive season in League Two. In addition to the domestic league, the club would also participate in the FA Cup, the EFL Cup, and the EFL Trophy.", "categories": [{"ns": 14, "title": "Category:2025–26 EFL League Two by team"}, {"ns": 14, "title": "Category:Articles with short description"}, {"ns": 14, "title": "Category:Pages using sports rbr table with an undescribed result"}, {"ns": 14, "title": "Category:Pages using sports rbr table with unequal row lengths"}, {"ns": 14, "title": "Category:Short description is different from Wikidata"}, {"ns": 14, "title": "Category:Short description matches Wikidata"}, {"ns": 14, "title": "Category:Swindon Town F.C. seasons"}]}}}, "limits": {"categories": 500}}