{"batchcomplete": "", "query": {"pages": {"73717021": {"pageid": 73717021, "ns": 0, "title": "List of Sikh footballers", "contentmodel": "wikitext", "pagelanguage": "en", "pagelanguagehtmlcode": "en", "pagelanguagedir": "ltr", "touched": "2026-02-04T20:25:39Z", "lastrevid": 1308710685, "length": 18499, "fullurl": "https://en.wikipedia.org/wiki/List_of_Sikh_footballers", "editurl": "https://en.wikipedia.org/w/index.php?title=List_of_Sikh_footballers&action=edit", "canonicalurl": "https://en.wikipedia.org/wiki/List_of_Sikh_footballers", "pageprops": {"wikibase-shortdesc": "", "wikibase_item": "Q118905520"}, "description": "", "descriptionsource": "local", "extract": "This is a list of Sikh footballers (soccer).", "categories": [{"ns": 14, "title": "Category:Articles with hCards"}, {"ns": 14, "title": "Category:Articles with short description"}, {"ns": 14, "title": "Category:Lists of association football players"}, {"ns": 14, "title": "Category:Short description is different from Wikidata"}, {"ns": 14, "title": "Category:Sikhism and sports"}, {"ns": 14, "title": "Category:Sikhs"}]}}}, "limits": {"categories": 500}}