{"batchcomplete": "", "query": {"pages": {"42894700": {"pageid": 42894700, "ns": 0, "title": "Joe Burgess", "contentmodel": "wikitext", "pagelanguage": "en", "pagelanguagehtmlcode": "en", "pagelanguagedir": "ltr", "touched": "2026-02-21T09:57:09Z", "lastrevid": 1339452736, "length": 22344, "fullurl": "https://en.wikipedia.org/wiki/Joe_Burgess", "editurl": "https://en.wikipedia.org/w/index.php?title=Joe_Burgess&action=edit", "canonicalurl": "https://en.wikipedia.org/wiki/Joe_Burgess", "pageprops": {"defaultsort": "Burgess, Joe", "page_image_free": "Joe_Burgess_and_a_Burgess_twin.jpg", "wikibase-shortdesc": "England international rugby league footballer", "wikibase_item": "Q16995395"}, "description": "England international rugby league footballer", "descriptionsource": "local", "extract": "Joe Burgess (born 14 October 1994) is an English rugby league footballer who plays as a winger for Hull Kingston Rovers in the Super League, and England at international level.\nHe previously spent two spells with the Wigan Warriors in the Super League, and has also played for the Sydney Roosters and the South Sydney Rabbitohs in the NRL.", "categories": [{"ns": 14, "title": "Category:1994 births"}, {"ns": 14, "title": "Category:21st-century English sportsmen"}, {"ns": 14, "title": "Category:All Wikipedia articles written in British English"}, {"ns": 14, "title": "Category:All articles with deprecated sources"}, {"ns": 14, "title": "Category:All articles with unsourced statements"}, {"ns": 14, "title": "Category:Articles with deprecated sources from February 2023"}, {"ns": 14, "title": "Category:Articles with short description"}, {"ns": 14, "title": "Category:Articles with unsourced statements from October 2022"}, {"ns": 14, "title": "Category:Commons category link from Wikidata"}, {"ns": 14, "title": "Category:England national rugby league team players"}, {"ns": 14, "title": "Category:English rugby league players"}, {"ns": 14, "title": "Category:Hull Kingston Rovers players"}, {"ns": 14, "title": "Category:Living people"}, {"ns": 14, "title": "Category:North Sydney Bears NSW Cup players"}, {"ns": 14, "title": "Category:Rugby league players from Wigan"}, {"ns": 14, "title": "Category:Rugby league wingers"}, {"ns": 14, "title": "Category:Salford RLFC players"}, {"ns": 14, "title": "Category:Short description is different from Wikidata"}, {"ns": 14, "title": "Category:South Sydney Rabbitohs players"}, {"ns": 14, "title": "Category:Sydney Roosters players"}, {"ns": 14, "title": "Category:Use British English from February 2020"}, {"ns": 14, "title": "Category:Use dmy dates from February 2020"}, {"ns": 14, "title": "Category:Wigan Warriors players"}]}}}, "limits": {"categories": 500}}