{"batchcomplete": "", "query": {"pages": {"5550432": {"pageid": 5550432, "ns": 0, "title": "David Hay", "contentmodel": "wikitext", "pagelanguage": "en", "pagelanguagehtmlcode": "en", "pagelanguagedir": "ltr", "touched": "2026-02-21T03:08:49Z", "lastrevid": 1293303464, "length": 14836, "fullurl": "https://en.wikipedia.org/wiki/David_Hay", "editurl": "https://en.wikipedia.org/w/index.php?title=David_Hay&action=edit", "canonicalurl": "https://en.wikipedia.org/wiki/David_Hay", "pageprops": {"defaultsort": "Hay, David", "page_image_free": "Davie_Hay_(1971).jpg", "wikibase-shortdesc": "Scottish footballer and manager", "wikibase_item": "Q2419390"}, "description": "Scottish footballer and manager", "descriptionsource": "local", "extract": "David Hay (born 29 January 1948) is a Scottish former football player and manager. He broke into the Celtic team in the late 1960s, as one of a generation of players who continued a highly successful era for the club. A contract dispute between Hay and Celtic led to him being transferred to Chelsea in 1974. He played in over 100 league games for Chelsea, but was forced to retire in 1979 due to a detached retina. Hay appeared in 27 international matches for Scotland, and was selected for their 1974 FIFA World Cup squad.\nAfter retiring as a player, Hay entered football management with Motherwell in 1981. He led them to a promotion in 1981–82, but left the club at the end of the season. He was then appointed Celtic manager in 1983, and enjoyed some success as they won the 1984–85 Scottish Cup and the Scottish league championship in 1985–86. In the 1990s he returned to Celtic as Chief Scout and later assistant general manager.\nHay also won the Norwegian league championship during a brief stint with Lillestrøm SK. He subsequently worked for St Mirren, Livingston and Dunfermline Athletic.", "categories": [{"ns": 14, "title": "Category:1948 births"}, {"ns": 14, "title": "Category:1974 FIFA World Cup players"}, {"ns": 14, "title": "Category:All Wikipedia articles written in British English"}, {"ns": 14, "title": "Category:Articles with short description"}, {"ns": 14, "title": "Category:Celtic F.C. managers"}, {"ns": 14, "title": "Category:Celtic F.C. players"}, {"ns": 14, "title": "Category:Chelsea F.C. players"}, {"ns": 14, "title": "Category:Dunfermline Athletic F.C. managers"}, {"ns": 14, "title": "Category:Eliteserien managers"}, {"ns": 14, "title": "Category:English Football League players"}, {"ns": 14, "title": "Category:Expatriate football managers in Norway"}, {"ns": 14, "title": "Category:Footballers from Paisley, Renfrewshire"}, {"ns": 14, "title": "Category:Lillestrøm SK managers"}, {"ns": 14, "title": "Category:Living people"}, {"ns": 14, "title": "Category:Livingston F.C. managers"}, {"ns": 14, "title": "Category:Livingston F.C. non-playing staff"}, {"ns": 14, "title": "Category:Men's association football midfielders"}, {"ns": 14, "title": "Category:Motherwell F.C. managers"}, {"ns": 14, "title": "Category:Pages using national squad without sport or team link"}, {"ns": 14, "title": "Category:People educated at St Mirin's Academy"}, {"ns": 14, "title": "Category:Scotland men's international footballers"}, {"ns": 14, "title": "Category:Scotland men's under-23 international footballers"}, {"ns": 14, "title": "Category:Scottish Football League managers"}, {"ns": 14, "title": "Category:Scottish Football League players"}, {"ns": 14, "title": "Category:Scottish Football League representative players"}, {"ns": 14, "title": "Category:Scottish Premier League managers"}, {"ns": 14, "title": "Category:Scottish expatriate football managers"}, {"ns": 14, "title": "Category:Scottish expatriate sportspeople in Norway"}, {"ns": 14, "title": "Category:Scottish football managers"}, {"ns": 14, "title": "Category:Scottish men's footballers"}, {"ns": 14, "title": "Category:Short description is different from Wikidata"}, {"ns": 14, "title": "Category:St Mirren F.C. managers"}, {"ns": 14, "title": "Category:Swindon Town F.C. non-playing staff"}, {"ns": 14, "title": "Category:Use British English from July 2013"}, {"ns": 14, "title": "Category:Use dmy dates from June 2023"}, {"ns": 14, "title": "Category:Watford F.C. non-playing staff"}]}}}, "limits": {"categories": 500}}