{"batchcomplete": "", "query": {"pages": {"151912": {"pageid": 151912, "ns": 0, "title": "All horses are the same color", "contentmodel": "wikitext", "pagelanguage": "en", "pagelanguagehtmlcode": "en", "pagelanguagedir": "ltr", "touched": "2026-02-13T14:04:40Z", "lastrevid": 1332916962, "length": 5959, "fullurl": "https://en.wikipedia.org/wiki/All_horses_are_the_same_color", "editurl": "https://en.wikipedia.org/w/index.php?title=All_horses_are_the_same_color&action=edit", "canonicalurl": "https://en.wikipedia.org/wiki/All_horses_are_the_same_color", "pageprops": {"wikibase-shortdesc": "Paradox arising from an incorrect proof", "wikibase_item": "Q1091396"}, "description": "Paradox arising from an incorrect proof", "descriptionsource": "local", "extract": "All horses are the same color is a falsidical paradox that arises from a flawed use of mathematical induction to prove the statement All horses are the same color. There is no actual contradiction, as these arguments have a crucial flaw that makes them incorrect. This example was originally raised by George Pólya in a 1954 book in different terms: \"Are any n numbers equal?\" or \"Any n girls have eyes of the same color\", as an exercise in mathematical induction. It has also been restated as \"All cows have the same color\".\nThe \"horses\" version of the paradox was presented in 1961 in a satirical article by Joel E. Cohen. It was stated as a lemma, which in particular allowed the author to \"prove\" that Alexander the Great did not exist, and he had an infinite number of limbs.", "categories": [{"ns": 14, "title": "Category:1961 introductions"}, {"ns": 14, "title": "Category:Articles with short description"}, {"ns": 14, "title": "Category:Color"}, {"ns": 14, "title": "Category:Horses in popular culture"}, {"ns": 14, "title": "Category:Inductive fallacies"}, {"ns": 14, "title": "Category:Mathematical humor"}, {"ns": 14, "title": "Category:Short description is different from Wikidata"}]}}}, "limits": {"categories": 500}}