{"batchcomplete": "", "query": {"pages": {"19760438": {"pageid": 19760438, "ns": 0, "title": "Mr. Men", "contentmodel": "wikitext", "pagelanguage": "en", "pagelanguagehtmlcode": "en", "pagelanguagedir": "ltr", "touched": "2026-02-26T21:26:25Z", "lastrevid": 1340642835, "length": 40578, "fullurl": "https://en.wikipedia.org/wiki/Mr._Men", "editurl": "https://en.wikipedia.org/w/index.php?title=Mr._Men&action=edit", "canonicalurl": "https://en.wikipedia.org/wiki/Mr._Men", "pageprops": {"defaultsort": "Mister Men", "displaytitle": "<i>Mr. Men</i>", "wikibase-shortdesc": "Children's book series", "wikibase_item": "Q2005333"}, "description": "Children's book series", "descriptionsource": "local", "extract": "Mr. Men is a British series of children's books and media franchise written and illustrated by English author Roger Hargreaves which began publication in August 1971. From 1981, an accompanying series of Little Miss books by the same author (but with female characters) was published. A similar series of animal characters known as Timbuctoo started in 1978. After Hargreaves's death in 1988, his son Adam Hargreaves began writing and illustrating new Mr. Men and Little Miss stories.\nEach book in the original Mr. Men and Little Miss series introduced a different title character and their single dominant personality trait to convey a simple moral lesson. The Mr. Men and Little Miss characters frequently reappeared in other characters' books. As of 2021, a total of 92 Mr. Men and Little Miss characters had been featured in the series. The books' simple stories, with brightly coloured, boldly drawn illustrations, have sold over 200 million copies worldwide across 28 countries.", "categories": [{"ns": 14, "title": "Category:1970s British animated television series"}, {"ns": 14, "title": "Category:1970s British children's television series"}, {"ns": 14, "title": "Category:1971 children's books"}, {"ns": 14, "title": "Category:1974 British television series debuts"}, {"ns": 14, "title": "Category:1974 animated television series debuts"}, {"ns": 14, "title": "Category:1980s British animated television series"}, {"ns": 14, "title": "Category:1980s British children's television series"}, {"ns": 14, "title": "Category:1983 British television series endings"}, {"ns": 14, "title": "Category:All Wikipedia articles written in British English"}, {"ns": 14, "title": "Category:All articles with dead external links"}, {"ns": 14, "title": "Category:All articles with incomplete citations"}, {"ns": 14, "title": "Category:All articles with unsourced statements"}, {"ns": 14, "title": "Category:All pages needing cleanup"}, {"ns": 14, "title": "Category:Articles with dead external links from September 2025"}, {"ns": 14, "title": "Category:Articles with incomplete citations from February 2026"}, {"ns": 14, "title": "Category:Articles with short description"}, {"ns": 14, "title": "Category:Articles with unsourced statements from March 2018"}, {"ns": 14, "title": "Category:BBC animated television series"}, {"ns": 14, "title": "Category:BBC children's television shows"}, {"ns": 14, "title": "Category:Book series introduced in 1971"}, {"ns": 14, "title": "Category:British English-language television shows"}, {"ns": 14, "title": "Category:British children's animated comedy television series"}, {"ns": 14, "title": "Category:British picture books"}, {"ns": 14, "title": "Category:British television shows based on children's books"}, {"ns": 14, "title": "Category:CS1 Japanese-language sources (ja)"}, {"ns": 14, "title": "Category:CS1 uses Japanese-language script (ja)"}, {"ns": 14, "title": "Category:Little Miss series"}, {"ns": 14, "title": "Category:Mr. Men series"}, {"ns": 14, "title": "Category:Sanrio characters"}, {"ns": 14, "title": "Category:Short description is different from Wikidata"}, {"ns": 14, "title": "Category:Use British English from September 2013"}, {"ns": 14, "title": "Category:Use dmy dates from February 2015"}, {"ns": 14, "title": "Category:Webarchive template wayback links"}, {"ns": 14, "title": "Category:Wikipedia indefinitely move-protected pages"}]}}}, "limits": {"categories": 500}}