{"batchcomplete": "", "query": {"pages": {"23025123": {"pageid": 23025123, "ns": 0, "title": "List of the first women ordained as priests in the Church of England in 1994", "contentmodel": "wikitext", "pagelanguage": "en", "pagelanguagehtmlcode": "en", "pagelanguagedir": "ltr", "touched": "2026-02-26T18:54:50Z", "lastrevid": 1319491942, "length": 11525, "fullurl": "https://en.wikipedia.org/wiki/List_of_the_first_women_ordained_as_priests_in_the_Church_of_England_in_1994", "editurl": "https://en.wikipedia.org/w/index.php?title=List_of_the_first_women_ordained_as_priests_in_the_Church_of_England_in_1994&action=edit", "canonicalurl": "https://en.wikipedia.org/wiki/List_of_the_first_women_ordained_as_priests_in_the_Church_of_England_in_1994", "pageprops": {"defaultsort": "List of women ordained as Church of England priests", "notoc": "", "page_image_free": "Ordination_of_women_plaque,_Bristol_Cathedral.jpg", "wikibase-shortdesc": "", "wikibase_item": "Q6643058"}, "description": "", "descriptionsource": "local", "extract": "On 12 March 1994, 32 women were ordained as Church of England priests for the first time in history. The service was officiated by Bishop Barry Rogerson at Bristol Cathedral.\nRogerson ordained the women in alphabetical order, so Angela Berners-Wilson was the very first woman to be ordained.\nThe youngest woman to be ordained was Karen MacKinnon at age 30, with Jean Kings being the second youngest. The oldest was 69.\nIn 2004 the tenth anniversary of the ordinations was celebrated at Bristol Cathedral and, by then, one of the priests had died and 14 had retired.\nThe 32 women ordained on the day were (list copied from the order of service):\n\nAngela Berners-Wilson, a university chaplain\nWaveney Bishop\nChristine Clarke\nJudith Creighton\nFaith Cully\nBrenda Dowie\nCarol Edwards, of St Christopher's, Brislington\nMargaret Embry\nAnnis Fessey\nJan Fortune-Wood\nSusan Giles\nJane Hayward\nJean Kings, part-time parish deacon who was also chaplain at University of the West of England\nKaren MacKinnon, full-time parish deacon\nAudrey Maddock\nCharmion Mann\nHelen Marshall\nGlenys Mills, Christ's Church, Clifton\nJillianne Norman\nClare Pipe-Wolferstan\nJune Plummer\nSusan Restall, St Mary's, Yate\nSusan Rose\nSusan Shipp\nMargery Simpson\nSylvia Stevens\nJudith Thompson\nAnita Thorne\nSheila Tyler\nPauline Wall\nRosemary Dawn Watling, at the time a 61-year-old Anglican nun and deacon in a vicarage in Bristol\nValerie Woods, Vicar of Wood End in Coventry\nIn 1994 a plaque was installed in Bristol Cathedral to mark these first 32 women ordained as priests in the Church of England. In 2022 it was replaced with a new plaque that listed the names of the women rather than only the names of the men who carried out the ceremony. Both plaques were carved in Welsh slate. The plaque is located on the north side of the nave where it meets the transept. The women contributed to the cost of the original plaque. The new one, carved by Robyn Golden-Hann, was unveiled by the Bishop of Bristol, Vivienne Faull.\nThe officiating bishop believed it would take 10 years before the first woman would be ordained as a bishop. In fact, it took 21 years until Libby Lane became the first female bishop in the Church of England as Bishop of Stockport (a suffragan see in the Diocese of Chester) in January 2015 (announced on 17 December 2014). Lane had also been ordained as a priest in 1994.\nThe first woman to be appointed diocesan bishop was the Right Reverend Rachel Treweek, Bishop of Gloucester, appointed on 26 March 2015. Treweek had been ordained as a priest in 1995.", "categories": [{"ns": 14, "title": "Category:All articles with dead external links"}, {"ns": 14, "title": "Category:Articles with dead external links from May 2017"}, {"ns": 14, "title": "Category:Articles with permanently dead external links"}, {"ns": 14, "title": "Category:Articles with short description"}, {"ns": 14, "title": "Category:Bristol Cathedral"}, {"ns": 14, "title": "Category:Church of England lists"}, {"ns": 14, "title": "Category:England-related lists"}, {"ns": 14, "title": "Category:Lists of firsts"}, {"ns": 14, "title": "Category:Lists of people associated with religion"}, {"ns": 14, "title": "Category:Lists of women's firsts"}, {"ns": 14, "title": "Category:Short description is different from Wikidata"}, {"ns": 14, "title": "Category:Use dmy dates from April 2022"}, {"ns": 14, "title": "Category:Women Anglican clergy"}]}}}, "limits": {"categories": 500}}