{"batchcomplete": "", "query": {"pages": {"50006062": {"pageid": 50006062, "ns": 0, "title": "Tony Hinchcliffe", "contentmodel": "wikitext", "pagelanguage": "en", "pagelanguagehtmlcode": "en", "pagelanguagedir": "ltr", "touched": "2026-02-21T03:12:38Z", "lastrevid": 1338558289, "length": 30643, "fullurl": "https://en.wikipedia.org/wiki/Tony_Hinchcliffe", "editurl": "https://en.wikipedia.org/w/index.php?title=Tony_Hinchcliffe&action=edit", "canonicalurl": "https://en.wikipedia.org/wiki/Tony_Hinchcliffe", "pageprops": {"defaultsort": "Hinchcliffe, Tony", "page_image_free": "Tony_Hinchcliffe_on_The_Comedy_Store_podcast_(cropped).jpg", "wikibase-shortdesc": "American comedian (born 1984)", "wikibase_item": "Q23772248"}, "description": "American comedian (born 1984)", "descriptionsource": "local", "extract": "Tony Hinchcliffe (born June 8, 1984) is an American comedian. Since 2013, he has hosted the live comedy podcast Kill Tony, a showcase of professional and amateur comedians who take turns doing one-minute sets. Hinchcliffe is known primarily for roast comedy, having been on the writing staff of the Comedy Central Roast series, and appearing at the All Def Digital Roast of Snoop Dogg in 2016 and The Roast of Tom Brady in 2024. He has released three comedy specials, One Shot on Netflix in 2016, Making Friends on YouTube in 2020, and Kill Tony: Kill or Be Killed on Netflix in 2025.\nHinchcliffe has a reputation for dark humor which, combined with his insult-based roast comedy, has led to several controversies. In 2021, he was dropped by his agency and lost multiple endorsements after using an anti-Asian slur against an opening Chinese American comedian during his set. In October 2024, the Donald Trump campaign invited him to perform a set at a rally at Madison Square Garden, during which he made a widely criticized joke about Puerto Rico.", "categories": [{"ns": 14, "title": "Category:1984 births"}, {"ns": 14, "title": "Category:21st-century American comedians"}, {"ns": 14, "title": "Category:21st-century people from Ohio"}, {"ns": 14, "title": "Category:All Wikipedia articles written in American English"}, {"ns": 14, "title": "Category:American male comedians"}, {"ns": 14, "title": "Category:American people of Italian descent"}, {"ns": 14, "title": "Category:American stand-up comedians"}, {"ns": 14, "title": "Category:Articles with hCards"}, {"ns": 14, "title": "Category:Articles with short description"}, {"ns": 14, "title": "Category:CS1: unfit URL"}, {"ns": 14, "title": "Category:Comedians from Ohio"}, {"ns": 14, "title": "Category:Commons category link from Wikidata"}, {"ns": 14, "title": "Category:Controversies of the 2024 United States presidential election"}, {"ns": 14, "title": "Category:Living people"}, {"ns": 14, "title": "Category:People associated with the 2024 United States presidential election"}, {"ns": 14, "title": "Category:People educated in Mahoning County, Ohio"}, {"ns": 14, "title": "Category:People from Youngstown, Ohio"}, {"ns": 14, "title": "Category:Short description is different from Wikidata"}, {"ns": 14, "title": "Category:Ursuline High School (Youngstown, Ohio) alumni"}, {"ns": 14, "title": "Category:Use American English from January 2026"}, {"ns": 14, "title": "Category:Use mdy dates from November 2024"}, {"ns": 14, "title": "Category:Wikipedia pages semi-protected against vandalism"}]}}}, "limits": {"categories": 500}}