{"batchcomplete": "", "query": {"pages": {"1097827": {"pageid": 1097827, "ns": 0, "title": "Art Davis (bassist)", "contentmodel": "wikitext", "pagelanguage": "en", "pagelanguagehtmlcode": "en", "pagelanguagedir": "ltr", "touched": "2026-02-19T15:12:30Z", "lastrevid": 1330241475, "length": 8926, "fullurl": "https://en.wikipedia.org/wiki/Art_Davis_(bassist)", "editurl": "https://en.wikipedia.org/w/index.php?title=Art_Davis_(bassist)&action=edit", "canonicalurl": "https://en.wikipedia.org/wiki/Art_Davis_(bassist)", "pageprops": {"defaultsort": "Davis, Art", "wikibase-shortdesc": "American double bassist", "wikibase_item": "Q705506"}, "description": "American double bassist", "descriptionsource": "local", "extract": "Arthur David Davis (December 5, 1934 – July 29, 2007) was a double-bassist, known for his work with Thelonious Monk, John Coltrane, Dizzy Gillespie, McCoy Tyner and Max Roach.", "categories": [{"ns": 14, "title": "Category:1934 births"}, {"ns": 14, "title": "Category:2007 deaths"}, {"ns": 14, "title": "Category:20th-century African-American musicians"}, {"ns": 14, "title": "Category:20th-century American double-bassists"}, {"ns": 14, "title": "Category:20th-century American jazz composers"}, {"ns": 14, "title": "Category:20th-century American male musicians"}, {"ns": 14, "title": "Category:21st-century African-American musicians"}, {"ns": 14, "title": "Category:American jazz double-bassists"}, {"ns": 14, "title": "Category:American male double-bassists"}, {"ns": 14, "title": "Category:American male jazz composers"}, {"ns": 14, "title": "Category:Articles with hCards"}, {"ns": 14, "title": "Category:Articles with short description"}, {"ns": 14, "title": "Category:Hard bop double-bassists"}, {"ns": 14, "title": "Category:Jazz musicians from Pennsylvania"}, {"ns": 14, "title": "Category:Musicians from Harrisburg, Pennsylvania"}, {"ns": 14, "title": "Category:Post-bop double-bassists"}, {"ns": 14, "title": "Category:Short description is different from Wikidata"}]}}}, "limits": {"categories": 500}}