{"batchcomplete": "", "query": {"pages": {"7010335": {"pageid": 7010335, "ns": 0, "title": "Tkachuk", "contentmodel": "wikitext", "pagelanguage": "en", "pagelanguagehtmlcode": "en", "pagelanguagedir": "ltr", "touched": "2026-02-26T06:40:18Z", "lastrevid": 1340351132, "length": 2125, "fullurl": "https://en.wikipedia.org/wiki/Tkachuk", "editurl": "https://en.wikipedia.org/w/index.php?title=Tkachuk&action=edit", "canonicalurl": "https://en.wikipedia.org/wiki/Tkachuk", "pageprops": {"wikibase-shortdesc": "Surname list", "wikibase_item": "Q96147050"}, "description": "Surname list", "descriptionsource": "local", "extract": "Tkachuk, Tkatchuk  (Ukrainian: Ткачук) is a common Ukrainian surname in Ukraine and the Ukrainian diaspora. The name in Ukrainian stands for the name of occupation, weaver. The names that end in -chuk or -czuk are of the western Ukrainian origin. Polish-language variant: Tkaczuk. Notable people with the surname include:\n\n", "categories": [{"ns": 14, "title": "Category:All set index articles"}, {"ns": 14, "title": "Category:Articles with short description"}, {"ns": 14, "title": "Category:Occupational surnames"}, {"ns": 14, "title": "Category:Short description is different from Wikidata"}, {"ns": 14, "title": "Category:Surnames"}, {"ns": 14, "title": "Category:Ukrainian-language surnames"}]}}}, "limits": {"categories": 500}}