{"batchcomplete": "", "query": {"pages": {"2771120": {"pageid": 2771120, "ns": 0, "title": "Patton Brothers", "contentmodel": "wikitext", "pagelanguage": "en", "pagelanguagehtmlcode": "en", "pagelanguagedir": "ltr", "touched": "2026-02-21T03:08:28Z", "lastrevid": 1331197732, "length": 5806, "fullurl": "https://en.wikipedia.org/wiki/Patton_Brothers", "editurl": "https://en.wikipedia.org/w/index.php?title=Patton_Brothers&action=edit", "canonicalurl": "https://en.wikipedia.org/wiki/Patton_Brothers", "pageprops": {"page_image_free": "The_Patton_Brothers_-_29-08-2013.jpg", "wikibase-shortdesc": "English comedy double act", "wikibase_item": "Q7148631"}, "description": "English comedy double act", "descriptionsource": "local", "extract": "The Patton Brothers, consisting of James (Jimmy) Elliott (20 August 1931 – 26 July 2019) and Brian Elliott (born 13 December 1933), were an English comedy double act and the two older brothers of Barry and Paul Elliott, the Chuckle Brothers. They began their career as a double act in the 1950s.", "categories": [{"ns": 14, "title": "Category:1931 births"}, {"ns": 14, "title": "Category:1933 births"}, {"ns": 14, "title": "Category:2019 deaths"}, {"ns": 14, "title": "Category:20th-century English male actors"}, {"ns": 14, "title": "Category:21st-century English male actors"}, {"ns": 14, "title": "Category:Actors from Rotherham"}, {"ns": 14, "title": "Category:All Wikipedia articles written in British English"}, {"ns": 14, "title": "Category:All articles needing additional references"}, {"ns": 14, "title": "Category:Articles needing additional references from November 2013"}, {"ns": 14, "title": "Category:Articles with hCards"}, {"ns": 14, "title": "Category:Articles with short description"}, {"ns": 14, "title": "Category:British parodists"}, {"ns": 14, "title": "Category:British slapstick comedians"}, {"ns": 14, "title": "Category:Brother duos"}, {"ns": 14, "title": "Category:Comedians from Kent"}, {"ns": 14, "title": "Category:Comedians from South Yorkshire"}, {"ns": 14, "title": "Category:English comedy duos"}, {"ns": 14, "title": "Category:English male comedians"}, {"ns": 14, "title": "Category:English male stage actors"}, {"ns": 14, "title": "Category:English male television actors"}, {"ns": 14, "title": "Category:Living people"}, {"ns": 14, "title": "Category:Male actors from Kent"}, {"ns": 14, "title": "Category:Male actors from South Yorkshire"}, {"ns": 14, "title": "Category:Pages using infobox person with multiple spouses"}, {"ns": 14, "title": "Category:Short description is different from Wikidata"}, {"ns": 14, "title": "Category:Use British English from July 2013"}, {"ns": 14, "title": "Category:Use dmy dates from October 2023"}]}}}, "limits": {"categories": 500}}