{"batchcomplete": "", "query": {"pages": {"8022366": {"pageid": 8022366, "ns": 0, "title": "Sarah Hoagland", "contentmodel": "wikitext", "pagelanguage": "en", "pagelanguagehtmlcode": "en", "pagelanguagedir": "ltr", "touched": "2026-02-26T18:02:24Z", "lastrevid": 1337526556, "length": 10676, "fullurl": "https://en.wikipedia.org/wiki/Sarah_Hoagland", "editurl": "https://en.wikipedia.org/w/index.php?title=Sarah_Hoagland&action=edit", "canonicalurl": "https://en.wikipedia.org/wiki/Sarah_Hoagland", "pageprops": {"defaultsort": "Hoagland, Sarah", "wikibase-shortdesc": "American philosopher (born 1945)", "wikibase_item": "Q7422394"}, "description": "American philosopher (born 1945)", "descriptionsource": "local", "extract": "Sarah Lucia Hoagland (born 4 June 1945 in Denver, Colorado) is the Bernard Brommel Distinguished Research Professor and Professor Emerita of Philosophy and Women's Studies at Northeastern Illinois University in Chicago.", "categories": [{"ns": 14, "title": "Category:1945 births"}, {"ns": 14, "title": "Category:20th-century American philosophers"}, {"ns": 14, "title": "Category:20th-century American women writers"}, {"ns": 14, "title": "Category:21st-century American non-fiction writers"}, {"ns": 14, "title": "Category:21st-century American philosophers"}, {"ns": 14, "title": "Category:21st-century American women writers"}, {"ns": 14, "title": "Category:All Wikipedia articles written in American English"}, {"ns": 14, "title": "Category:All articles lacking reliable references"}, {"ns": 14, "title": "Category:American feminist writers"}, {"ns": 14, "title": "Category:American gender studies academics"}, {"ns": 14, "title": "Category:American lesbian writers"}, {"ns": 14, "title": "Category:American philosophy academics"}, {"ns": 14, "title": "Category:American women non-fiction writers"}, {"ns": 14, "title": "Category:American women philosophers"}, {"ns": 14, "title": "Category:Anti-pornography feminists"}, {"ns": 14, "title": "Category:Articles lacking reliable references from January 2011"}, {"ns": 14, "title": "Category:Articles with hCards"}, {"ns": 14, "title": "Category:Articles with short description"}, {"ns": 14, "title": "Category:BLP articles lacking sources from January 2011"}, {"ns": 14, "title": "Category:Feminist studies scholars"}, {"ns": 14, "title": "Category:LGBTQ people from Colorado"}, {"ns": 14, "title": "Category:LGBTQ philosophers"}, {"ns": 14, "title": "Category:Lambda Literary Award winners"}, {"ns": 14, "title": "Category:Lesbian academics"}, {"ns": 14, "title": "Category:Lesbian feminists"}, {"ns": 14, "title": "Category:Lesbian separatists"}, {"ns": 14, "title": "Category:Living people"}, {"ns": 14, "title": "Category:Northeastern Illinois University faculty"}, {"ns": 14, "title": "Category:People from Denver"}, {"ns": 14, "title": "Category:Radical feminists"}, {"ns": 14, "title": "Category:Scholars of feminist philosophy"}, {"ns": 14, "title": "Category:Short description is different from Wikidata"}, {"ns": 14, "title": "Category:Use American English from February 2026"}, {"ns": 14, "title": "Category:Webarchive template wayback links"}]}}}, "limits": {"categories": 500}}