{"query": {"search": [{"ns": 0, "title": "Antonio Tejero", "pageid": 546269, "size": 17541, "wordcount": 1704, "snippet": "<span class=\"searchmatch\">Antonio</span> <span class=\"searchmatch\">Tejero</span> <span class=\"searchmatch\">Molina</span> (30 April 1932 – 25 February 2026) was a Spanish lieutenant colonel of the Guardia Civil. He was the most prominent figure in the", "timestamp": "2026-02-27T09:14:37Z"}, {"ns": 0, "title": "1981 Spanish coup attempt", "pageid": 546272, "size": 48151, "wordcount": 5637, "snippet": "in Spain as 23F, began on 23 February 1981 when Lieutenant-Colonel <span class=\"searchmatch\">Antonio</span> <span class=\"searchmatch\">Tejero</span>, along with 200 armed Civil Guard officers, stormed the Congress of", "timestamp": "2026-02-27T09:57:43Z"}, {"ns": 0, "title": "Molina (surname)", "pageid": 1290722, "size": 8748, "wordcount": 1122, "snippet": "Academy Antonio Sebastián de Toledo <span class=\"searchmatch\">Molina</span> y Salazar (1625–1710), viceroy of New Spain 1664–1673 <span class=\"searchmatch\">Antonio</span> <span class=\"searchmatch\">Tejero</span> <span class=\"searchmatch\">Molina</span> (born 1932), Spanish Lieutenant-Colonel", "timestamp": "2026-01-29T03:58:08Z"}, {"ns": 0, "title": "Civil Guard (Spain)", "pageid": 325008, "size": 43272, "wordcount": 3950, "snippet": "the end of the twentieth century: on 23 February 1981, Lt. Col. <span class=\"searchmatch\">Antonio</span> <span class=\"searchmatch\">Tejero</span> <span class=\"searchmatch\">Molina</span>, a member of the Guardia Civil, participated with other military", "timestamp": "2026-02-25T12:12:54Z"}, {"ns": 0, "title": "February 1981", "pageid": 2705319, "size": 30886, "wordcount": 3756, "snippet": "Guardia Civil. A disgruntled Spanish Army officer, Lieutenant Colonel <span class=\"searchmatch\">Antonio</span> <span class=\"searchmatch\">Tejero</span> <span class=\"searchmatch\">Molina</span> led the seizure of the Cortes building and took 347 legislators", "timestamp": "2026-02-17T09:37:08Z"}, {"ns": 0, "title": "Mariano Vidal Molina", "pageid": 64215752, "size": 5862, "wordcount": 611, "snippet": "Miller (1973), by Juan <span class=\"searchmatch\">Antonio</span> Bardem, Carola de día, Carola de noche (1969), by Jaime de Armiñán, along Frank Braña, Charito <span class=\"searchmatch\">Tejero</span>, José Canalejas, Tomás", "timestamp": "2026-02-13T01:39:02Z"}, {"ns": 0, "title": "40th Goya Awards", "pageid": 80568812, "size": 27444, "wordcount": 905, "snippet": "Belén Aguilera, Bad Gyal, Dani Fernández, La Casa Azul, Ana Mena, Alba <span class=\"searchmatch\">Molina</span>, and Ángeles Toledano as well as by the co-host Rigoberta Bandini were announced", "timestamp": "2026-02-27T10:58:45Z"}, {"ns": 0, "title": "Crimen Ferpecto", "pageid": 7208007, "size": 7485, "wordcount": 582, "snippet": "Cervera [es] as Lourdes Luis Varela [es] as Don <span class=\"searchmatch\">Antonio</span> Enrique Villén as Inspector Campoy Fernando <span class=\"searchmatch\">Tejero</span> as Alonso Javier Gutiérrez as Jaime Kira Miró", "timestamp": "2025-12-27T19:59:12Z"}, {"ns": 0, "title": "Héctor Alterio", "pageid": 2724017, "size": 16444, "wordcount": 1609, "snippet": "home [es] was attended by family members and colleagues such as Fernando <span class=\"searchmatch\">Tejero</span>, Lola Herrera, Natalia Dicenta, Juan Diego Botto, Luisa Martín, Juana Acosta", "timestamp": "2026-01-19T11:19:48Z"}, {"ns": 0, "title": "Madrid Forum", "pageid": 69454377, "size": 35996, "wordcount": 2476, "snippet": "Brazilian Eduardo Bolsonaro, Peruvian Keiko Fujimori and Chilean Jose <span class=\"searchmatch\">Antonio</span> Kast. The Charter alerts that countries “hijacked by communist-inspired", "timestamp": "2026-02-21T19:48:57Z"}]}, "continue": {"sroffset": 10, "continue": "-||"}}