{"batchcomplete": "", "query": {"pages": {"395736": {"pageid": 395736, "ns": 0, "title": "Tony Iommi", "contentmodel": "wikitext", "pagelanguage": "en", "pagelanguagehtmlcode": "en", "pagelanguagedir": "ltr", "touched": "2026-02-22T12:08:19Z", "lastrevid": 1339193205, "length": 78391, "fullurl": "https://en.wikipedia.org/wiki/Tony_Iommi", "editurl": "https://en.wikipedia.org/w/index.php?title=Tony_Iommi&action=edit", "canonicalurl": "https://en.wikipedia.org/wiki/Tony_Iommi", "pageprops": {"defaultsort": "Iommi, Tony", "page_image_free": "Tony-Iommi_2009-06-11_Chicago_photoby_Adam-Bielawski.jpg", "wikibase-shortdesc": "British rock guitarist (born 1948)", "wikibase_item": "Q202733"}, "description": "British rock guitarist (born 1948)", "descriptionsource": "local", "extract": "Anthony Frank Iommi Jr. (; born 19 February 1948) is an English musician. He co-founded the pioneering heavy metal band Black Sabbath in 1968, and was the guitarist, leader, main composer, and only constant member during the band's existence for over fifty years, playing guitar on all of their releases. He is considered one of the creators of heavy metal music and has been referred to as the \"Godfather of Heavy Metal\".\nAs a teen, Iommi lost the tips of his right-hand ring and middle fingers in a work accident at a sheet metal factory, which influenced his distinct playing style. He down-tuned his guitar and used more power chords (partly to make playing easier), and made much use of the tritone (or 'devil's interval'), resulting in a 'heavier' and 'darker' sound that became a hallmark of heavy metal. As well as Black Sabbath, he was briefly live guitarist for Jethro Tull in 1968. Iommi intended Seventh Star (1986) to be his first solo album, but the record label decided to release it under the Black Sabbath name. In 2000, he released his first official solo album Iommi, followed in 2005 by Fused, which featured former bandmate Glenn Hughes. In 2006 Iommi formed Heaven & Hell with former Black Sabbath bandmates. They released The Devil You Know (2009), before disbanding after the death of singer Ronnie James Dio in 2010.\nIommi is widely regarded as one of the greatest and most influential rock guitarists of all time. He has won many awards, including three Grammy Awards and a Lifetime Achievement Award from the National Guitar Museum, and is honoured on the Birmingham Walk of Stars. In 2011, Iommi published his autobiography, entitled Iron Man: My Journey Through Heaven and Hell with Black Sabbath.", "categories": [{"ns": 14, "title": "Category:1948 births"}, {"ns": 14, "title": "Category:20th-century English guitarists"}, {"ns": 14, "title": "Category:20th-century English songwriters"}, {"ns": 14, "title": "Category:20th-century Roman Catholics"}, {"ns": 14, "title": "Category:21st-century English guitarists"}, {"ns": 14, "title": "Category:21st-century English songwriters"}, {"ns": 14, "title": "Category:21st-century Roman Catholics"}, {"ns": 14, "title": "Category:All BLP articles lacking sources"}, {"ns": 14, "title": "Category:All Wikipedia articles written in British English"}, {"ns": 14, "title": "Category:All articles containing potentially dated statements"}, {"ns": 14, "title": "Category:All articles with unsourced statements"}, {"ns": 14, "title": "Category:Articles containing potentially dated statements from August 2016"}, {"ns": 14, "title": "Category:Articles with hCards"}, {"ns": 14, "title": "Category:Articles with short description"}, {"ns": 14, "title": "Category:Articles with unsourced statements from January 2019"}, {"ns": 14, "title": "Category:BLP articles lacking sources from August 2020"}, {"ns": 14, "title": "Category:Black Sabbath members"}, {"ns": 14, "title": "Category:British musicians of Italian descent"}, {"ns": 14, "title": "Category:British musicians with disabilities"}, {"ns": 14, "title": "Category:Commons category link from Wikidata"}, {"ns": 14, "title": "Category:English Roman Catholics"}, {"ns": 14, "title": "Category:English autobiographers"}, {"ns": 14, "title": "Category:English blues rock musicians"}, {"ns": 14, "title": "Category:English heavy metal guitarists"}, {"ns": 14, "title": "Category:English lead guitarists"}, {"ns": 14, "title": "Category:English male songwriters"}, {"ns": 14, "title": "Category:English people of Italian descent"}, {"ns": 14, "title": "Category:English people with disabilities"}, {"ns": 14, "title": "Category:English rock guitarists"}, {"ns": 14, "title": "Category:Grammy Award winners"}, {"ns": 14, "title": "Category:Heaven & Hell (band) members"}, {"ns": 14, "title": "Category:Jethro Tull (band) members"}, {"ns": 14, "title": "Category:Living people"}, {"ns": 14, "title": "Category:Musicians from Birmingham, West Midlands"}, {"ns": 14, "title": "Category:People from Aston"}, {"ns": 14, "title": "Category:People from Handsworth, West Midlands"}, {"ns": 14, "title": "Category:Short description is different from Wikidata"}, {"ns": 14, "title": "Category:Short description matches Wikidata"}, {"ns": 14, "title": "Category:Use British English from October 2024"}, {"ns": 14, "title": "Category:Use dmy dates from October 2024"}, {"ns": 14, "title": "Category:Webarchive template wayback links"}, {"ns": 14, "title": "Category:Wikipedia articles needing page number citations from February 2013"}]}}}, "limits": {"categories": 500}}