{"batchcomplete": "", "query": {"pages": {"1939118": {"pageid": 1939118, "ns": 0, "title": "Michael Duncan", "contentmodel": "wikitext", "pagelanguage": "en", "pagelanguagehtmlcode": "en", "pagelanguagedir": "ltr", "touched": "2026-02-16T21:30:56Z", "lastrevid": 1338724268, "length": 357, "fullurl": "https://en.wikipedia.org/wiki/Michael_Duncan", "editurl": "https://en.wikipedia.org/w/index.php?title=Michael_Duncan&action=edit", "canonicalurl": "https://en.wikipedia.org/wiki/Michael_Duncan", "pageprops": {"disambiguation": "", "wikibase-shortdesc": "Topics referred to by the same term", "wikibase_item": "Q6829987"}, "description": "Topics referred to by the same term", "descriptionsource": "local", "extract": "Michael Duncan may refer to:\n\nMichael Clarke Duncan (1957–2012), American actor\nMike Duncan (politician) (born 1951), chairman of the Republican National Committee\nMike Duncan (podcaster) (born 1980), American podcaster\nMike Duncan (racing driver) (born 1962), American stock car racing driver", "categories": [{"ns": 14, "title": "Category:All article disambiguation pages"}, {"ns": 14, "title": "Category:All disambiguation pages"}, {"ns": 14, "title": "Category:Human name disambiguation pages"}, {"ns": 14, "title": "Category:Short description is different from Wikidata"}]}}}, "limits": {"categories": 500}}