{"batchcomplete": "", "query": {"pages": {"31997066": {"pageid": 31997066, "ns": 0, "title": "List of The Walking Dead (TV series) characters", "contentmodel": "wikitext", "pagelanguage": "en", "pagelanguagehtmlcode": "en", "pagelanguagedir": "ltr", "touched": "2026-02-26T19:17:59Z", "lastrevid": 1334921948, "length": 296294, "fullurl": "https://en.wikipedia.org/wiki/List_of_The_Walking_Dead_(TV_series)_characters", "editurl": "https://en.wikipedia.org/w/index.php?title=List_of_The_Walking_Dead_(TV_series)_characters&action=edit", "canonicalurl": "https://en.wikipedia.org/wiki/List_of_The_Walking_Dead_(TV_series)_characters", "pageprops": {"defaultsort": "List Of Walking Dead Characters", "displaytitle": "List of <i>The Walking Dead</i> (TV series) characters", "page_image_free": "Andrew_Lincoln,_Greg_Nicotero,_Norman_Reedus,_Melissa_McBride,_Lennie_James,_Chandler_Riggs,_Jeffrey_Dean_Morgan,_Lauren_Cohan,_Alanna_Masterson_&_Seth_Gilliam_(cropped).jpg", "wikibase-shortdesc": "", "wikibase_item": "Q59646"}, "description": "", "descriptionsource": "local", "extract": "The following is a list of characters from The Walking Dead television series based on the eponymous comic book series. Although some characters appear in both the television and comic series, the continuity of the television series is not shared with the original comic book series.\n\n", "categories": [{"ns": 14, "title": "Category:All articles needing additional references"}, {"ns": 14, "title": "Category:All articles needing rewrite"}, {"ns": 14, "title": "Category:All articles that are excessively detailed"}, {"ns": 14, "title": "Category:All articles with style issues"}, {"ns": 14, "title": "Category:All articles with unsourced statements"}, {"ns": 14, "title": "Category:Articles needing additional references from October 2018"}, {"ns": 14, "title": "Category:Articles with multiple maintenance issues"}, {"ns": 14, "title": "Category:Articles with short description"}, {"ns": 14, "title": "Category:Articles with unsourced statements from November 2013"}, {"ns": 14, "title": "Category:CS1: unfit URL"}, {"ns": 14, "title": "Category:Lists of American drama television series characters"}, {"ns": 14, "title": "Category:Lists of horror television characters"}, {"ns": 14, "title": "Category:Short description is different from Wikidata"}, {"ns": 14, "title": "Category:The Walking Dead (TV series)"}, {"ns": 14, "title": "Category:The Walking Dead (franchise) characters"}, {"ns": 14, "title": "Category:Use mdy dates from March 2020"}, {"ns": 14, "title": "Category:Wikipedia articles needing rewrite from February 2019"}, {"ns": 14, "title": "Category:Wikipedia articles that are excessively detailed from February 2019"}, {"ns": 14, "title": "Category:Wikipedia articles with style issues from February 2019"}, {"ns": 14, "title": "Category:Wikipedia pages semi-protected from banned users"}]}}}, "limits": {"categories": 500}}